{
  "generated_date": "2026-01-30",
  "week_ending": "January 30, 2026",
  "divisions": {
    "premier_league": {
      "name": "Premier League",
      "articles": [
        {
          "title": "Everything you need to know about the Champions League play-off draw",
          "link": "https://www.bbc.com/sport/football/articles/c77kmg1xnp4o?at_medium=RSS&at_campaign=rss",
          "published": "2026-01-30",
          "summary": "BBC Sport's Ask Me Anything team explains how the Champions League knockout phase play-offs work and when the draw is taking place.",
          "image": "https://ichef.bbci.co.uk/ace/standard/240/cpsprodpb/220d/live/3fd21a30-fad4-11f0-a422-4ba8a094a8fa.jpg"
        },
        {
          "title": "Journalist dreams & Keane reunion? How O'Neill continues to revive Celtic",
          "link": "https://www.bbc.com/sport/football/articles/cn42dpdx1edo?at_medium=RSS&at_campaign=rss",
          "published": "2026-01-30",
          "summary": "Showman Martin O'Neill continues to thrive as Celtic's interim manager as he guides the club through to the Europa League play-off round.",
          "image": "https://ichef.bbci.co.uk/ace/standard/240/cpsprodpb/b791/live/74b85930-fd68-11f0-a00a-0545b9d7ca40.jpg"
        },
        {
          "title": "How do Liverpool fix their struggles against low blocks?",
          "link": "https://www.bbc.com/sport/football/articles/cew8qnqqgqzo?at_medium=RSS&at_campaign=rss",
          "published": "2026-01-30",
          "summary": "Why are Liverpool struggling against low blocks in the Premier League, how are they trying to unlock them and what could they do better?",
          "image": "https://ichef.bbci.co.uk/ace/standard/240/cpsprodpb/9508/live/dce7c940-fd0f-11f0-833e-6bf0186607ca.jpg"
        },
        {
          "title": "Can you name every team still in the Champions League?",
          "link": "https://www.bbc.com/sport/football/articles/cg7y4r5d3lno?at_medium=RSS&at_campaign=rss",
          "published": "2026-01-30",
          "summary": "The Champions League knockout phase gets under way with the play-off first legs on 17 and 18 February - can you name all 24 teams still in the competition?",
          "image": "https://ichef.bbci.co.uk/ace/standard/240/cpsprodpb/9a72/live/b1bd2190-fdb7-11f0-b7e1-afb6d0884c18.jpg"
        },
        {
          "title": "Keeper-turned-striker Steele still inspired by Ferguson rocket",
          "link": "https://www.bbc.com/sport/football/articles/cpwne85ng97o?at_medium=RSS&at_campaign=rss",
          "published": "2026-01-30",
          "summary": "Former Manchester United goalkeeper Luke Steele, once given a training-ground rocket by Sir Alex Ferguson, is now banging in the goals in non-league aged 41.",
          "image": "https://ichef.bbci.co.uk/ace/standard/240/cpsprodpb/99f1/live/c691f010-fdbb-11f0-b724-c371fd414c33.jpg"
        },
        {
          "title": "Pato interest shows strength of English game - Cowley",
          "link": "https://www.bbc.com/sport/football/articles/c4gwynynpnmo?at_medium=RSS&at_campaign=rss",
          "published": "2026-01-30",
          "summary": "Alexandre Pato's interest in Colchester United underlines the overall strength of the English football pyramid, says manager Danny Cowley.",
          "image": "https://ichef.bbci.co.uk/ace/standard/240/cpsprodpb/43e1/live/f8e1c960-fdb5-11f0-8e3f-176b350fc659.jpg"
        },
        {
          "title": "Dangerman Makhmudov a threat in 'dream fight' against Fury?",
          "link": "https://www.skysports.com/boxing/news/12040/13500815/tyson-fury-under-threat-meet-the-heavyweight-dangerman-arslanbek-makhmudov-taking-on-fury-in-comeback-fight",
          "published": "2026-01-30",
          "summary": "Few boxers can match the towering Tyson Fury for size and stature. But the imposing Arslanbek Makhmudov gets close.",
          "image": "https://e1.365dm.com/25/10/1920x1080/skysports-arslanbek-makhmudov_7048354.jpg?20251011133508"
        },
        {
          "title": "Sutton's predictions v boxer Francesca Hennessy",
          "link": "https://www.bbc.com/sport/football/articles/cx204g4rn8xo?at_medium=RSS&at_campaign=rss",
          "published": "2026-01-29",
          "summary": "BBC Sport football expert Chris Sutton takes on boxer Francesca Hennessy and AI with his predictions for this week's Premier League fixtures.",
          "image": "https://ichef.bbci.co.uk/ace/standard/240/cpsprodpb/b2d0/live/3345b7f0-fd30-11f0-a8b8-bdd2c5f9bcad.png"
        },
        {
          "title": "Who is 'shy and nervous' Villa match-winner Jimoh-Aloba?",
          "link": "https://www.bbc.com/sport/football/articles/c8j32vezyylo?at_medium=RSS&at_campaign=rss",
          "published": "2026-01-29",
          "summary": "Aston Villa match-winner Jamaldeen Jimoh-Aloba is described as \"shy and nervous\" by Morgan Rogers - but the teenager announced himself on the European stage.",
          "image": "https://ichef.bbci.co.uk/ace/standard/240/cpsprodpb/66d8/live/86b31130-fd62-11f0-9c09-35264ee739f3.jpg"
        },
        {
          "title": "What happened in final round of Europa League matches?",
          "link": "https://www.bbc.com/sport/football/articles/c62015dell5o?at_medium=RSS&at_campaign=rss",
          "published": "2026-01-29",
          "summary": "Your guide to the teams that made the top eight, the 16 clubs in the play-offs and the sides who have been eliminated from the Europa League.",
          "image": "https://ichef.bbci.co.uk/ace/standard/240/cpsprodpb/0956/live/d7289e20-fd5b-11f0-809e-0391886361ed.jpg"
        },
        {
          "title": "'Barca move gave me confidence I could adapt'",
          "link": "https://www.bbc.com/sport/football/videos/czx32x07lzzo?at_medium=RSS&at_campaign=rss",
          "published": "2026-01-29",
          "summary": "Chelsea's Lucy Bronze - England's most decorated female footballer - tells BBC Sport's Emma Sanders that she \"found even more confidence in myself\" after leaving Manchester City in 2022.",
          "image": "https://ichef.bbci.co.uk/ace/standard/240/cpsprodpb/64aa/live/8703e040-fc65-11f0-9972-d3f265c101c6.jpg"
        },
        {
          "title": "How English clubs got smart to dominate this season's Champions League",
          "link": "https://www.bbc.com/sport/football/articles/c9qp21lej5zo?at_medium=RSS&at_campaign=rss",
          "published": "2026-01-29",
          "summary": "Premier League clubs always had the money, but now they also have the know-how they have dominated this season's Champions League.",
          "image": "https://ichef.bbci.co.uk/ace/standard/240/cpsprodpb/b523/live/ecc723e0-fd20-11f0-8de9-b9e0f3a8919a.jpg"
        },
        {
          "title": "Senegal boss Thiaw banned after Afcon final chaos",
          "link": "https://www.bbc.com/sport/football/articles/c24gy9d52vno?at_medium=RSS&at_campaign=rss",
          "published": "2026-01-29",
          "summary": "Senegal manager Pape Thiaw his banned for five games after the chaotic scenes during the Africa Cup of Nations final against Morocco.",
          "image": "https://ichef.bbci.co.uk/ace/standard/240/cpsprodpb/2921/live/05d22f60-fce0-11f0-b827-6fb9814e291f.jpg"
        },
        {
          "title": "Bompastor tracks back on WSL title 'gone' comments",
          "link": "https://www.bbc.com/sport/football/articles/clye0zq328no?at_medium=RSS&at_campaign=rss",
          "published": "2026-01-29",
          "summary": "Chelsea manager Sonia Bompastor has tracked back on her comments saying the WSL title is \"probably over\" by insisting her side will \"never give up\".",
          "image": "https://ichef.bbci.co.uk/ace/standard/240/cpsprodpb/63eb/live/d15fa4e0-fd2c-11f0-890b-55ca0a00c59d.jpg"
        },
        {
          "title": "England on course for fifth Champions League spot",
          "link": "https://www.bbc.com/sport/football/articles/cj0npqv9rylo?at_medium=RSS&at_campaign=rss",
          "published": "2026-01-29",
          "summary": "Could the Premier League get an extra place in the Champions League again? This is how it looks at the end of the league phases.",
          "image": "https://ichef.bbci.co.uk/ace/standard/240/cpsprodpb/93c9/live/5b39a1a0-fc67-11f0-a7b3-13a56b7a31f4.jpg"
        }
      ],
      "highlights": [
        {
          "title": "Premier League highlights this week - Week Highlights",
          "search_url": "https://www.youtube.com/results?search_query=Premier+League+highlights+this+week",
          "embed_id": null
        }
      ]
    },
    "championship": {
      "name": "Championship",
      "articles": [
        {
          "title": "Scottish Championship top two set for battle - live on BBC",
          "link": "https://www.bbc.com/sport/football/articles/crml0de20v9o?at_medium=RSS&at_campaign=rss",
          "published": "2026-01-30",
          "summary": "St Johnstone against Partick Thistle on Friday night - live on the BBC - will go some way to deciding the Scottish Championship title.",
          "image": "https://ichef.bbci.co.uk/ace/standard/240/cpsprodpb/6da8/live/f93eedb0-fd2a-11f0-890b-55ca0a00c59d.jpg"
        },
        {
          "title": "Littler named PDC Player of the Year as part of awards hat-trick",
          "link": "https://www.skysports.com/darts/news/12040/13500869/luke-littler-named-pdc-player-of-the-year-as-part-of-awards-hat-trick",
          "published": "2026-01-29",
          "summary": "Luke Littler picked up three accolades at the PDC's Annual Awards after his World Championship-winning triumph earlier this month.",
          "image": "https://e2.365dm.com/26/01/1920x1080/skysports-luke-littler-darts_7125642.jpg?20260130073916"
        },
        {
          "title": "He'll come back with VENGEANCE!' | Brundle backs Piastri to claim maiden championship",
          "link": "https://www.skysports.com/watch/video/13500822/i-think-he-will-come-back-with-vengeance-martin-brundle-backs-oscar-piastri-to-claim-maiden-championship",
          "published": "2026-01-29",
          "summary": "Martin Brundle backs Oscar Piastri to claim his maiden championship!",
          "image": "https://e1.365dm.com/26/01/1920x1080/skysports-martin-brundle-oscar-p_7149888.jpg?20260129215138"
        }
      ],
      "highlights": [
        {
          "title": "Championship highlights this week - Week Highlights",
          "search_url": "https://www.youtube.com/results?search_query=Championship+highlights+this+week",
          "embed_id": null
        }
      ]
    },
    "league_one": {
      "name": "League One",
      "articles": [],
      "highlights": [
        {
          "title": "League One highlights this week - Week Highlights",
          "search_url": "https://www.youtube.com/results?search_query=League+One+highlights+this+week",
          "embed_id": null
        }
      ]
    },
    "league_two": {
      "name": "League Two",
      "articles": [],
      "highlights": [
        {
          "title": "League Two highlights this week - Week Highlights",
          "search_url": "https://www.youtube.com/results?search_query=League+Two+highlights+this+week",
          "embed_id": null
        }
      ]
    },
    "world_cup": {
      "name": "World Cup",
      "articles": [
        {
          "title": "Highlights: South Africa pip England in first match of series",
          "link": "https://www.skysports.com/watch/video/13500750/south-africa-52-48-england-netball-international-series-highlights",
          "published": "2026-01-29",
          "summary": "Highlights of the Vitality Roses' first match of their three -game international series against South Africa.",
          "image": "https://e0.365dm.com/26/01/1920x1080/skysports-england-netball-south-africa-netball_7149726.jpg?20260129181248"
        }
      ],
      "highlights": [
        {
          "title": "World Cup highlights this week - Week Highlights",
          "search_url": "https://www.youtube.com/results?search_query=World+Cup+highlights+this+week",
          "embed_id": null
        }
      ]
    }
  },
  "standout_moments": [
    {
      "moment": "How 'superb' Fernandes led Man Utd to win at Arsenal",
      "link": "https://www.bbc.com/sport/football/videos/c2lgw7n2yewo?at_medium=RSS&at_campaign=rss"
    },
    {
      "moment": "Six of the most memorable goalkeeper goals",
      "link": "https://www.bbc.com/sport/football/articles/c2d7yjwgex4o?at_medium=RSS&at_campaign=rss"
    },
    {
      "moment": "Littler named PDC Player of the Year as part of awards hat-trick",
      "link": "https://www.skysports.com/darts/news/12040/13500869/luke-littler-named-pdc-player-of-the-year-as-part-of-awards-hat-trick"
    }
  ]
}