{
  "generated_date": "2026-07-02",
  "week_ending": "July 02, 2026",
  "divisions": {
    "premier_league": {
      "name": "Premier League",
      "articles": [
        {
          "title": "'You can't catch your breath' - how will Azteca altitude impact England?",
          "link": "https://www.bbc.co.uk/sport/football/articles/c4gy0v05qyro?at_medium=RSS&at_campaign=rss",
          "published": "2026-07-02",
          "summary": "BBC Sport explores how playing football at high altitude affects the body and mind as England prepare to visit Mexico and their fortress Azteca Stadium.",
          "image": "https://ichef.bbci.co.uk/ace/standard/240/cpsprodpb/0010/live/08736230-73f4-11f1-bb7f-e5226e63ffb3.jpg"
        },
        {
          "title": "Balogun gives USA deserved lead over Bosnia",
          "link": "https://www.bbc.co.uk/sport/football/videos/c77ymxvm8kdo?at_medium=RSS&at_campaign=rss",
          "published": "2026-07-02",
          "summary": "Folarin Balogun gives the USA the lead against Bosnia-Herzegovina in their round of 32 match at the San Francisco Bay Area Stadium.",
          "image": "https://ichef.bbci.co.uk/ace/standard/240/cpsprodpb/a28d/live/da5830f0-75b1-11f1-9510-1546718f668b.jpg"
        },
        {
          "title": "Football Daily",
          "link": "https://www.bbc.co.uk/sounds/play/p0ns844v?at_medium=RSS&at_campaign=rss",
          "published": "2026-07-02",
          "summary": "England are through... now the Azteca awaits.",
          "image": "https://ichef.bbci.co.uk/images/ic/240x135/p0ntl4qr.jpg"
        },
        {
          "title": "All the angles of Kane's brilliant winner",
          "link": "https://www.bbc.co.uk/sport/football/videos/cgev83898nzo?at_medium=RSS&at_campaign=rss",
          "published": "2026-07-01",
          "summary": "All the angles of Harry Kane's winning goal against DR Congo for England in their round of 32 game in Atlanta.",
          "image": "https://ichef.bbci.co.uk/ace/standard/240/cpsprodpb/4e24/live/4be946d0-7587-11f1-a627-714adb4eed6e.jpg"
        },
        {
          "title": "Tielemans & Trossard go from heated row to rescuing Belgium",
          "link": "https://www.bbc.co.uk/sport/football/videos/cvg512g38g4o?at_medium=RSS&at_campaign=rss",
          "published": "2026-07-01",
          "summary": "Belgium's Leandro Trossard and Youri Tielemans go from arguing with each other during the hydration break to combining to get a crucial equalising goal against Senegal in Seattle.",
          "image": "https://ichef.bbci.co.uk/ace/standard/240/cpsprodpb/99bc/live/9ed21350-75a4-11f1-9510-1546718f668b.jpg"
        },
        {
          "title": "Tielemans scores late extra-time penalty to send Belgium into last 16",
          "link": "https://www.bbc.co.uk/sport/football/videos/cvg7kdx1vpno?at_medium=RSS&at_campaign=rss",
          "published": "2026-07-01",
          "summary": "Belgium score two late goals to force extra time against Senegal where Youri Tielemans scores a late penalty following a VAR review as Belgium win 3-2 to reach the last 16.",
          "image": "https://ichef.bbci.co.uk/ace/standard/240/cpsprodpb/d0b0/live/c8ebea30-759f-11f1-9510-1546718f668b.jpg"
        },
        {
          "title": "Tielemans scores late extra-time penalty in dramatic end to match",
          "link": "https://www.bbc.co.uk/sport/football/videos/c1wy5wwpxw7o?at_medium=RSS&at_campaign=rss",
          "published": "2026-07-01",
          "summary": "Youri Tielemans scores a dramatic late penalty in extra time to see Belgium advance to the last 16 after a 3-2 victory over Senegal in Seattle.",
          "image": "https://ichef.bbci.co.uk/ace/standard/240/cpsprodpb/1bd8/live/ccacc5f0-75a3-11f1-a627-714adb4eed6e.jpg"
        },
        {
          "title": "Energy and team spirit at highest level - Tuchel",
          "link": "https://www.bbc.co.uk/sport/football/videos/cg53njjvnljo?at_medium=RSS&at_campaign=rss",
          "published": "2026-07-01",
          "summary": "England manager Thomas Tuchel praises his sides team spirit as they come from behind to beat DR Congo 2-1 and advance to the round of 16.",
          "image": "https://ichef.bbci.co.uk/ace/standard/240/cpsprodpb/65de/live/36d422b0-757d-11f1-9510-1546718f668b.jpg"
        },
        {
          "title": "Relief for England as Kane heads in equalising goal against DR Congo",
          "link": "https://www.bbc.co.uk/sport/football/videos/cg4wg7lee1vo?at_medium=RSS&at_campaign=rss",
          "published": "2026-07-01",
          "summary": "Harry Kane heads in from Anthony Gordon's cross as England equalise against DR Congo in their round of 32 game in Atlanta.",
          "image": "https://ichef.bbci.co.uk/ace/standard/240/cpsprodpb/d0d4/live/bcb01af0-7574-11f1-a627-714adb4eed6e.jpg"
        },
        {
          "title": "Chelsea sign Italy defender Palestra for \u00a347m",
          "link": "https://www.bbc.co.uk/sport/football/articles/crkvlv6myreo?at_medium=RSS&at_campaign=rss",
          "published": "2026-07-01",
          "summary": "Right-back Marco Palestra, 21, becomes Xabi Alonso's first signing as Chelsea manager.",
          "image": "https://ichef.bbci.co.uk/ace/standard/240/cpsprodpb/3b2b/live/2e843280-7203-11f1-a031-6f45322bb16f.jpg"
        },
        {
          "title": "The small Basque club that produced Arteta, Alonso and Iraola",
          "link": "https://www.bbc.co.uk/sport/football/articles/cr5j40gr44mo?at_medium=RSS&at_campaign=rss",
          "published": "2026-07-01",
          "summary": "The Arsenal, Chelsea and Liverpool managers all began their football journeys in the Basque region",
          "image": "https://ichef.bbci.co.uk/ace/standard/240/cpsprodpb/b7c7/live/89d11a70-6436-11f1-a936-d75187a800c2.jpg"
        },
        {
          "title": "Hull avoid points deduction by selling  players",
          "link": "https://www.bbc.co.uk/sport/football/articles/c5yz5dprjq0o?at_medium=RSS&at_campaign=rss",
          "published": "2026-07-01",
          "summary": "Hull City avoided the threat of a points deduction in the Premier League by selling two players hours before Tuesday's deadline.",
          "image": "https://ichef.bbci.co.uk/ace/standard/240/cpsprodpb/22aa/live/15ccd0a0-7486-11f1-a63e-8369d3f8e6b7.jpg"
        },
        {
          "title": "Harry Kane: England's greatest and Ballon d'Or contender",
          "link": "https://www.skysports.com/football/news/12040/13559651/harry-kane-england-captain-shows-why-he-is-greatest-every-striker-and-ballon-dor-contender-after-two-goal-heroics-against-dr-congo",
          "published": "2026-07-01",
          "summary": "Yes, England have issues. They put you through the mill, they're struggling for a right-back. But one problem they don't have is having a world-class matchwinner in their team.",
          "image": "https://e0.365dm.com/26/07/1920x1080/skysports-kane-harry-england_7287772.jpg?20260702071825"
        }
      ],
      "highlights": [
        {
          "title": "Premier League highlights this week - Week Highlights",
          "search_url": "https://www.youtube.com/results?search_query=Premier+League+highlights+this+week",
          "embed_id": null
        }
      ]
    },
    "championship": {
      "name": "Championship",
      "articles": [
        {
          "title": "Sunderland and Palace hunting Real and PSG in WC goal charts!",
          "link": "https://www.skysports.com/football/news/12040/13558909/world-cup-2026-how-many-goals-have-players-from-premier-league-clubs-scored",
          "published": "2026-06-30",
          "summary": "Which teams' players have scored the most goals at the World Cup so far?",
          "image": "https://e1.365dm.com/26/07/1920x1080/skysports-graphic-world-cup_7287057.jpg?20260701072559"
        }
      ],
      "highlights": [
        {
          "title": "Championship highlights this week - Week Highlights",
          "search_url": "https://www.youtube.com/results?search_query=Championship+highlights+this+week",
          "embed_id": null
        }
      ]
    },
    "league_one": {
      "name": "League One",
      "articles": [],
      "highlights": [
        {
          "title": "League One highlights this week - Week Highlights",
          "search_url": "https://www.youtube.com/results?search_query=League+One+highlights+this+week",
          "embed_id": null
        }
      ]
    },
    "league_two": {
      "name": "League Two",
      "articles": [],
      "highlights": [
        {
          "title": "League Two highlights this week - Week Highlights",
          "search_url": "https://www.youtube.com/results?search_query=League+Two+highlights+this+week",
          "embed_id": null
        }
      ]
    },
    "world_cup": {
      "name": "World Cup",
      "articles": [
        {
          "title": "Goalscorer Balogun sent off for USA",
          "link": "https://www.bbc.co.uk/sport/football/videos/cpv3xzyr73po?at_medium=RSS&at_campaign=rss",
          "published": "2026-07-02",
          "summary": "USA forward Folarin Balogun is shown a straight red card for a challenge on Bosnia-Herzegovina's Tarik Muharemovic during their World Cup match.",
          "image": "https://ichef.bbci.co.uk/ace/standard/240/cpsprodpb/a2a7/live/01b21190-75ba-11f1-a627-714adb4eed6e.jpg"
        },
        {
          "title": "Lopes will relish Messi duel, says Cape Verde defender's mother",
          "link": "https://www.bbc.co.uk/sport/football/articles/c07yjj5j299o?at_medium=RSS&at_campaign=rss",
          "published": "2026-07-02",
          "summary": "The prospect of facing World Cup record goalscorer Lionel Messi in a knockout game would strike fear into most defenders, but not Roberto Lopes, according to the Cape Verde defender's mother.",
          "image": "https://ichef.bbci.co.uk/ace/standard/240/cpsprodpb/bc48/live/d3d67f60-751c-11f1-adcf-e1eef1a1ef9c.jpg"
        },
        {
          "title": "Merse: Mexico is heads-or-tails match - they could run England off their feet",
          "link": "https://www.skysports.com/football/news/12040/13559758/mexico-vs-england-world-cup-last-16-tie-is-heads-or-tails-match-they-could-run-us-off-our-feet-says-paul-merson",
          "published": "2026-07-02",
          "summary": "Sky Sports' Paul Merson looks ahead to England's last-16 World Cup encounter with co-hosts Mexico on Monday, a game he thinks is too close to call.",
          "image": "https://e0.365dm.com/26/07/1920x1080/skysports-world-cup-merson-says_7287983.jpg?20260702115239"
        },
        {
          "title": "Tuchel urges parents to let kids stay up for England game",
          "link": "https://www.bbc.co.uk/sport/football/articles/cd95g9y8k24o?at_medium=RSS&at_campaign=rss",
          "published": "2026-07-01",
          "summary": "England manager Thomas Tuchel urges parents to let their children stay up to watch England take on Mexico in the last 16 of the World Cup.",
          "image": "https://ichef.bbci.co.uk/ace/standard/240/cpsprodpb/2496/live/92ee8fb0-7599-11f1-a627-714adb4eed6e.jpg"
        },
        {
          "title": "Genuine superstar Kane produces his biggest England moment",
          "link": "https://www.bbc.co.uk/sport/football/articles/cvgd12vj79qo?at_medium=RSS&at_campaign=rss",
          "published": "2026-07-01",
          "summary": "Harry Kane's England career is filled with great moments - his World Cup rescue act against DR Congo in Atlanta is his greatest, says chief football writer Phil McNulty.",
          "image": "https://ichef.bbci.co.uk/ace/standard/240/cpsprodpb/43ec/live/5b4fe1a0-75dd-11f1-b2ef-f150187f763a.jpg"
        },
        {
          "title": "'He is ridiculous' - Rice praise for match-winner Kane",
          "link": "https://www.bbc.co.uk/sport/football/videos/cgmdlrrgezjo?at_medium=RSS&at_campaign=rss",
          "published": "2026-07-01",
          "summary": "Declan Rice describes England captain Harry Kane as \"ridiculous\" after he scores twice during their World Cup victory over DR Congo in Atlanta.",
          "image": "https://ichef.bbci.co.uk/ace/standard/240/cpsprodpb/19df/live/8a18c9a0-7580-11f1-b976-0b9c15b0ccfc.jpg"
        },
        {
          "title": "Has football fever taken hold in the US?",
          "link": "https://www.bbc.co.uk/sport/football/articles/c4gyr0y37ndo?at_medium=RSS&at_campaign=rss",
          "published": "2026-07-01",
          "summary": "With the World Cup now three weeks old, BBC Sport's reporters in the US look at how their perceptions have changed.",
          "image": "https://ichef.bbci.co.uk/ace/standard/240/cpsprodpb/84db/live/2ba6f6d0-74ae-11f1-9c5b-41132a229f02.jpg"
        },
        {
          "title": "'A huge advantage for Mexico' - England face an Azteca altitude problem",
          "link": "https://www.skysports.com/football/news/12040/13559666/mexico-vs-england-thomas-tuchels-side-face-a-huge-altitude-problem-by-playing-world-cup-round-of-16-at-7000-feet",
          "published": "2026-07-01",
          "summary": "\"It is one of the most beautiful fixtures you can have playing Mexico in the Azteca,\" said Thomas Tuchel after England booked their World Cup last 16 spot. But it is also one of the hardest fixtures i...",
          "image": "https://e0.365dm.com/26/07/1920x1080/skysports-england-mexico-azteca-stadium_7288006.jpg?20260702120417"
        }
      ],
      "highlights": [
        {
          "title": "World Cup highlights this week - Week Highlights",
          "search_url": "https://www.youtube.com/results?search_query=World+Cup+highlights+this+week",
          "embed_id": null
        }
      ]
    }
  },
  "standout_moments": [
    {
      "moment": "Tielemans scores late extra-time penalty in dramatic end to match",
      "link": "https://www.bbc.co.uk/sport/football/videos/c1wy5wwpxw7o?at_medium=RSS&at_campaign=rss"
    },
    {
      "moment": "Lopes will relish Messi duel, says Cape Verde defender's mother",
      "link": "https://www.bbc.co.uk/sport/football/articles/c07yjj5j299o?at_medium=RSS&at_campaign=rss"
    }
  ]
}