{
  "generated_date": "2025-12-21",
  "week_ending": "December 21, 2025",
  "divisions": {
    "premier_league": {
      "name": "Premier League",
      "articles": [
        {
          "title": "Can Aston Villa sustain a title challenge?",
          "link": "https://www.bbc.com/sport/football/videos/cd9z5qlveq1o?at_medium=RSS&at_campaign=rss",
          "published": "2025-12-21",
          "summary": "Football Focus's Alex Scott, Nedum Onuoha and Glenn Murray look at Aston Villa's incredible Premier League form and whether they can sustain a title challenge this season.",
          "image": "https://ichef.bbci.co.uk/ace/standard/240/cpsprodpb/d95e/live/2da5a730-ddb7-11f0-aae2-2191c0e48a3b.jpg"
        },
        {
          "title": "Who are the contenders to win Afcon?",
          "link": "https://www.bbc.com/sport/football/videos/clyde53vkjro?at_medium=RSS&at_campaign=rss",
          "published": "2025-12-21",
          "summary": "BBC Sport's John Bennett gives Football Focus the lowdown on which nations are contenders to win the Africa Cup of Nations, which begins in Morocco on Sunday.",
          "image": "https://ichef.bbci.co.uk/ace/standard/240/cpsprodpb/3f6a/live/06885630-ddb6-11f0-aae2-2191c0e48a3b.jpg"
        },
        {
          "title": "Given shares Howe's frustrations on trio of decisions",
          "link": "https://www.bbc.com/sport/football/videos/czj08kjpev3o?at_medium=RSS&at_campaign=rss",
          "published": "2025-12-21",
          "summary": "Match of the Day's Shay Given shares Newcastle manager Eddie Howe's frustrations after a trio of decisions went against the Magpies in their 2-2 draw with Chelsea.",
          "image": "https://ichef.bbci.co.uk/ace/standard/240/cpsprodpb/a665/live/0d11cc60-ddfd-11f0-aae2-2191c0e48a3b.jpg"
        },
        {
          "title": "How Man City smothered West Ham with 'suffocating' press",
          "link": "https://www.bbc.com/sport/football/videos/c0edy98j588o?at_medium=RSS&at_campaign=rss",
          "published": "2025-12-21",
          "summary": "Match of the Day's Joe Hart looks at Manchester City's \"suffocating\" press as they looked back to their dominant best in a 3-0 win over West Ham.",
          "image": "https://ichef.bbci.co.uk/ace/standard/240/cpsprodpb/5311/live/1d385c70-ddfe-11f0-b67b-690eb873de1b.jpg"
        },
        {
          "title": "Gyokores penalty sends Arsenal top of the table in win against Everton",
          "link": "https://www.bbc.com/sport/football/videos/crrk125ezw4o?at_medium=RSS&at_campaign=rss",
          "published": "2025-12-20",
          "summary": "Arsenal striker Viktor Gyokores' first-half penalty sends the Gunners to the top of the Premier League table in win over Everton.",
          "image": "https://ichef.bbci.co.uk/ace/standard/240/cpsprodpb/87a7/live/73269600-ddf5-11f0-a8dc-93c15fe68710.jpg"
        },
        {
          "title": "Liverpool hold on to beat nine-man Spurs",
          "link": "https://www.bbc.com/sport/football/videos/c4g98ldpx5qo?at_medium=RSS&at_campaign=rss",
          "published": "2025-12-20",
          "summary": "Substitute Alexander Isak scores for Liverpool before being forced off with injury as Arne Slot's side win a chaotic Premier League match at nine-man Tottenham.",
          "image": "https://ichef.bbci.co.uk/ace/standard/240/cpsprodpb/7d62/live/f0bfa570-ddeb-11f0-aae2-2191c0e48a3b.jpg"
        },
        {
          "title": "Calvert-Lewin scores twice as Leeds thrash Crystal Palace",
          "link": "https://www.bbc.com/sport/football/videos/cwylx542dnjo?at_medium=RSS&at_campaign=rss",
          "published": "2025-12-20",
          "summary": "Dominic Calvert-Lewin extends his scoring streak to five Premier League games with a superb double as Leeds United secure a comfortable victory over Crystal Palace at Elland Road.",
          "image": "https://ichef.bbci.co.uk/ace/standard/240/cpsprodpb/8cdd/live/12333570-ddf4-11f0-aae2-2191c0e48a3b.jpg"
        },
        {
          "title": "Haaland scores twice as Man City beat West Ham",
          "link": "https://www.bbc.com/sport/football/videos/cd0krv8pzkgo?at_medium=RSS&at_campaign=rss",
          "published": "2025-12-20",
          "summary": "Erling Haaland scores twice to help Manchester City beat beleaguered West Ham United for a fifth straight Premier League victory which moved them top of the table.",
          "image": "https://ichef.bbci.co.uk/ace/standard/240/cpsprodpb/37ac/live/2bea63d0-ddd1-11f0-aae2-2191c0e48a3b.jpg"
        },
        {
          "title": "Broja heads home late equaliser for Burnley at Bournemouth",
          "link": "https://www.bbc.com/sport/football/videos/cy845pn8lnno?at_medium=RSS&at_campaign=rss",
          "published": "2025-12-20",
          "summary": "Armando Broja heads home a dramatic late equaliser as struggling Burnley end their seven-game losing streak by claiming a precious Premier League point at Bournemouth.",
          "image": "https://ichef.bbci.co.uk/ace/standard/240/cpsprodpb/4160/live/bd154730-dddb-11f0-a8dc-93c15fe68710.jpg"
        },
        {
          "title": "Brighton & Sunderland's first ever PL match ends in 0-0 draw",
          "link": "https://www.bbc.com/sport/football/videos/cdxed5p8xlko?at_medium=RSS&at_campaign=rss",
          "published": "2025-12-20",
          "summary": "Brighton's disappointing December run continues as they played out a goalless draw against Sunderland in the Premier League.",
          "image": "https://ichef.bbci.co.uk/ace/standard/240/cpsprodpb/a276/live/d09ea060-ddd3-11f0-aae2-2191c0e48a3b.jpg"
        },
        {
          "title": "Top and bottom at Christmas - what does it mean?",
          "link": "https://www.bbc.com/sport/football/articles/c87lqlw9ej2o?at_medium=RSS&at_campaign=rss",
          "published": "2025-12-20",
          "summary": "As we approach the halfway point of the season, what do the ghosts of Christmas past tell us about the Premier League title race and relegation battle?",
          "image": "https://ichef.bbci.co.uk/ace/standard/240/cpsprodpb/0b3b/live/afdefa70-ddf4-11f0-9faa-bb36d4d42b5c.png"
        },
        {
          "title": "'Do we want to be remembered for fighting or being cowards?'",
          "link": "https://www.bbc.com/sport/football/articles/c9qe27vx781o?at_medium=RSS&at_campaign=rss",
          "published": "2025-12-20",
          "summary": "Relegation from the Premier League looks inevitable for Wolves after a 15th defeat in 17 games - but will they avoid setting more unwanted records?",
          "image": "https://ichef.bbci.co.uk/ace/standard/240/cpsprodpb/44c4/live/6b38ceb0-ddcb-11f0-b1cd-b1a770a93709.jpg"
        },
        {
          "title": "Maresca hints at wanting older heads at end of chaotic week",
          "link": "https://www.bbc.com/sport/football/articles/c20kynlj473o?at_medium=RSS&at_campaign=rss",
          "published": "2025-12-20",
          "summary": "Blues manager Enzo Maresca hints that having some more experience in his squad would be beneficial following their comeback to earn a point at Newcastle.",
          "image": "https://ichef.bbci.co.uk/ace/standard/240/cpsprodpb/a0fc/live/0e89c3d0-dda4-11f0-aa29-47e19247c473.jpg"
        },
        {
          "title": "Were Newcastle denied 'stonewall' penalty against Chelsea?",
          "link": "https://www.bbc.com/sport/articles/c1e4ylydx15o?at_medium=RSS&at_campaign=rss",
          "published": "2025-12-20",
          "summary": "Newcastle United manager Eddie Howe says his side were denied a \"stonewall\" penalty in their 2-2 draw with Chelsea - so, does he have a point?",
          "image": "https://ichef.bbci.co.uk/ace/standard/240/cpsprodpb/2d59/live/99d55fd0-ddcc-11f0-b67b-690eb873de1b.jpg"
        },
        {
          "title": "Afcon to be held every four years from 2028",
          "link": "https://www.bbc.com/sport/football/articles/cgjnx6x4281o?at_medium=RSS&at_campaign=rss",
          "published": "2025-12-20",
          "summary": "In a huge change to the football calendar, the Africa Cup of Nations will be held every four years from 2028 - switching away from biennial finals.",
          "image": "https://ichef.bbci.co.uk/ace/standard/240/cpsprodpb/4b66/live/81c39bb0-d1c8-11f0-9c0d-83f64f80aa08.jpg"
        }
      ],
      "highlights": [
        {
          "title": "Premier League highlights this week - Week Highlights",
          "search_url": "https://www.youtube.com/results?search_query=Premier+League+highlights+this+week",
          "embed_id": null
        }
      ]
    },
    "championship": {
      "name": "Championship",
      "articles": [
        {
          "title": "'Luke is a different breed' - The NHS worker looking to upset Littler",
          "link": "https://www.skysports.com/darts/news/12040/13485657/luke-littler-nhs-worker-david-davies-says-teenager-is-a-different-breed-as-he-aims-to-cause-major-upset-at-world-darts-championship",
          "published": "2025-12-21",
          "summary": "David Davies says Luke Littler is a &#8220;different breed&#8221; but is hoping to cause a major upset when the pair meet in the second round of the World Darts Championship on Sunday night.",
          "image": "https://e2.365dm.com/25/12/1920x1080/skysports-darts-luke-littler_7115716.jpg?20251220114957"
        },
        {
          "title": "Former winner Smith sent packing as emotional Bunting marches on",
          "link": "https://www.skysports.com/darts/news/12040/13485981/world-darts-championship-former-winner-michael-smith-sent-packing-as-peoples-champion-stephen-bunting-marches-through-to-third-round",
          "published": "2025-12-20",
          "summary": "Former winner Michael Smith was sent packing from the World Darts Championship on Saturday as an emotional Stephen Bunting marched through.",
          "image": "https://e0.365dm.com/25/12/1920x1080/skysports-michael-smith-darts_7116418.jpg?20251220220223"
        },
        {
          "title": "Team Kuchar hold two-shot lead over Team Daly at PNC Championship",
          "link": "https://www.skysports.com/golf/news/12040/13486260/pnc-championship-matt-kuchar-and-son-cameron-lead-john-daly-and-son-john-daly-ii-in-florida",
          "published": "2025-12-20",
          "summary": "Matt Kuchar and his college-bound son Cameron made birdie on all but three holes for a 15-under 57 to build a two-shot lead over John Daly and his college son in the PNC Championship on Saturday.",
          "image": "https://e1.365dm.com/25/12/1920x1080/skysports-matt-kuchar-pnc-championship_7116483.jpg?20251220234308"
        }
      ],
      "highlights": [
        {
          "title": "Championship highlights this week - Week Highlights",
          "search_url": "https://www.youtube.com/results?search_query=Championship+highlights+this+week",
          "embed_id": null
        }
      ]
    },
    "league_one": {
      "name": "League One",
      "articles": [],
      "highlights": [
        {
          "title": "League One highlights this week - Week Highlights",
          "search_url": "https://www.youtube.com/results?search_query=League+One+highlights+this+week",
          "embed_id": null
        }
      ]
    },
    "league_two": {
      "name": "League Two",
      "articles": [],
      "highlights": [
        {
          "title": "League Two highlights this week - Week Highlights",
          "search_url": "https://www.youtube.com/results?search_query=League+Two+highlights+this+week",
          "embed_id": null
        }
      ]
    },
    "world_cup": {
      "name": "World Cup",
      "articles": [],
      "highlights": [
        {
          "title": "World Cup highlights this week - Week Highlights",
          "search_url": "https://www.youtube.com/results?search_query=World+Cup+highlights+this+week",
          "embed_id": null
        }
      ]
    }
  },
  "standout_moments": [
    {
      "moment": "Broja heads home late equaliser for Burnley at Bournemouth",
      "link": "https://www.bbc.com/sport/football/videos/cy845pn8lnno?at_medium=RSS&at_campaign=rss"
    },
    {
      "moment": "'Do we want to be remembered for fighting or being cowards?'",
      "link": "https://www.bbc.com/sport/football/articles/c9qe27vx781o?at_medium=RSS&at_campaign=rss"
    },
    {
      "moment": "Maresca hints at wanting older heads at end of chaotic week",
      "link": "https://www.bbc.com/sport/football/articles/c20kynlj473o?at_medium=RSS&at_campaign=rss"
    },
    {
      "moment": "'Luke is a different breed' - The NHS worker looking to upset Littler",
      "link": "https://www.skysports.com/darts/news/12040/13485657/luke-littler-nhs-worker-david-davies-says-teenager-is-a-different-breed-as-he-aims-to-cause-major-upset-at-world-darts-championship"
    }
  ]
}