{
  "generated_date": "2026-02-23",
  "week_ending": "February 23, 2026",
  "divisions": {
    "premier_league": {
      "name": "Premier League",
      "articles": [
        {
          "title": "Saka and Timber partnership among 'best in Europe'",
          "link": "https://www.bbc.com/sport/football/videos/cy4wn2z2255o?at_medium=RSS&at_campaign=rss",
          "published": "2026-02-23",
          "summary": "Match of the Day pundit Danny Murphy looks at how the combination of Bukayo Saka and Jurrien Timber down the right side tormented Tottenham's defence in Arsenal's 4-1 win over their north London rival...",
          "image": "https://ichef.bbci.co.uk/ace/standard/240/cpsprodpb/7c11/live/46d37600-1044-11f1-9120-a910fc22c6ac.jpg"
        },
        {
          "title": "Spurs' league position is a 'big concern' - Rooney",
          "link": "https://www.bbc.com/sport/football/videos/cgl5zld2wxzo?at_medium=RSS&at_campaign=rss",
          "published": "2026-02-23",
          "summary": "Wayne Rooney discusses the possibility of Tottenham Hotspur getting relegated this season.",
          "image": "https://ichef.bbci.co.uk/ace/standard/240/cpsprodpb/670a/live/c405abb0-109a-11f1-801d-ed3cff6bf876.jpg"
        },
        {
          "title": "Referee disallowed Spurs goal for 'soft' push - Given",
          "link": "https://www.bbc.com/sport/football/videos/c20zp25g85yo?at_medium=RSS&at_campaign=rss",
          "published": "2026-02-23",
          "summary": "Match of the Day pundits Shay Given and Danny Murphy believe Tottenham \"have a reason to be disappointed\" with Randal Kolo Muani's second 'goal' being ruled out for a foul on Arsenal defender Gabriel.",
          "image": "https://ichef.bbci.co.uk/ace/standard/240/cpsprodpb/c087/live/83fbc860-1045-11f1-9120-a910fc22c6ac.jpg"
        },
        {
          "title": "How Liverpool shook off 'horrendous' start to beat Forest",
          "link": "https://www.bbc.com/sport/football/videos/cvg14dn3d9go?at_medium=RSS&at_campaign=rss",
          "published": "2026-02-23",
          "summary": "Match of the Day pundits Danny Murphy and Shay Given compare Liverpool's \"flat\" first-half performance against Nottingham Forest with their match-winning display in the second period.",
          "image": "https://ichef.bbci.co.uk/ace/standard/240/cpsprodpb/1cb0/live/28c8f940-104a-11f1-801d-ed3cff6bf876.jpg"
        },
        {
          "title": "Quiz: Name these footballers who have played for Man Utd and Everton",
          "link": "https://www.bbc.com/sport/football/articles/c2k8qw1v92po?at_medium=RSS&at_campaign=rss",
          "published": "2026-02-23",
          "summary": "Name all 17 players who have made at least one Premier League appearance for both Everton and Manchester United.",
          "image": "https://ichef.bbci.co.uk/ace/standard/240/cpsprodpb/a79c/live/8bb42b50-0f10-11f1-b048-c9424b2cf5fd.jpg"
        },
        {
          "title": "Littler victory in Poland can fuel Premier League comeback in Belfast",
          "link": "https://www.skysports.com/darts/news/12040/13510833/luke-littler-believes-victory-in-poland-can-fuel-a-premier-league-darts-comeback-starting-in-belfast-on-thursday",
          "published": "2026-02-23",
          "summary": "Luke Littler believes his sensational victory at the inaugural SUPERBET Poland Darts Open can fuel a Premier League comeback - starting in Belfast on Thursday.",
          "image": "https://e0.365dm.com/26/02/1920x1080/skysports-luke-littler-darts_7152715.jpg?20260205154507"
        },
        {
          "title": "Papers: Man Utd legend confirms talk for Old Trafford return",
          "link": "https://www.skysports.com/football/news/12040/13511013/bukayo-saka-injury-concern-emerges-for-arsenal-after-limping-off-during-tottenham-win-paper-talk-and-football-transfer-gossip",
          "published": "2026-02-23",
          "summary": "The top stories and transfer rumours from Monday's newspapers...",
          "image": "https://e1.365dm.com/25/03/1920x1080/skysports-paper-talk-brand-refresh_6852897.jpg?20250311094415"
        },
        {
          "title": "'Appalling weekend' - Arokodare & Mundle latest players to be racially abused",
          "link": "https://www.bbc.com/sport/football/articles/cz6egezw1d3o?at_medium=RSS&at_campaign=rss",
          "published": "2026-02-22",
          "summary": "Wolves striker Tolu Arokodare and Sunderland winger Romaine Mundle have become the latest Premier League players to be sent racist abuse on social media this weekend.",
          "image": "https://ichef.bbci.co.uk/ace/standard/240/cpsprodpb/dc2c/live/3b5260e0-103d-11f1-b048-c9424b2cf5fd.png"
        },
        {
          "title": "Old Firm 'buckle under pressure' as incredible title race twists again",
          "link": "https://www.bbc.com/sport/football/articles/cx24kgz91wjo?at_medium=RSS&at_campaign=rss",
          "published": "2026-02-22",
          "summary": "After a defeat for Celtic and surprise draw for Rangers, where does the latest weekend of drama leave the Scottish Premiership title race?",
          "image": "https://ichef.bbci.co.uk/ace/standard/240/cpsprodpb/2c5f/live/a7493660-102a-11f1-b048-c9424b2cf5fd.png"
        },
        {
          "title": "'Heist' at Forest boosts Liverpool's top-four hopes",
          "link": "https://www.bbc.com/sport/articles/c3v7de0zvnyo?at_medium=RSS&at_campaign=rss",
          "published": "2026-02-22",
          "summary": "Liverpool's late 1-0 win at Nottingham Forest puts the Reds firmly in the Champions League hunt after a \"robbery\" of a victory at the City Ground.",
          "image": "https://ichef.bbci.co.uk/ace/standard/240/cpsprodpb/9495/live/b07aa310-1019-11f1-b048-c9424b2cf5fd.jpg"
        },
        {
          "title": "Arsenal pass derby test of nerve as title race looks set to go to wire",
          "link": "https://www.bbc.com/sport/football/articles/cx2g3gq37xvo?at_medium=RSS&at_campaign=rss",
          "published": "2026-02-22",
          "summary": "Arsenal passed the north London derby test with flying colours as Premier League title race looks likely to go to the wire, says chief football writer Phil McNulty",
          "image": "https://ichef.bbci.co.uk/ace/standard/240/cpsprodpb/2843/live/a246d9f0-1026-11f1-ab85-f7fb8d09b1b3.jpg"
        },
        {
          "title": "It's absolutely OK to face fans' criticism - Glasner",
          "link": "https://www.bbc.com/sport/football/articles/cx2g3gy12v5o?at_medium=RSS&at_campaign=rss",
          "published": "2026-02-22",
          "summary": "Oliver Glasner says it is \"absolutely OK\" to \"face criticism\" after some Crystal Palace fans again questioned his immediate future as manager.",
          "image": "https://ichef.bbci.co.uk/ace/standard/240/cpsprodpb/08b6/live/75225390-1009-11f1-b946-cf1a9157ff12.jpg"
        },
        {
          "title": "Eze 'wanted to prove something' as he torments Spurs again",
          "link": "https://www.bbc.com/sport/football/articles/crk861mm643o?at_medium=RSS&at_campaign=rss",
          "published": "2026-02-22",
          "summary": "For those who have followed Eberechi Eze's career, the sight of him wheeling away to celebrate an important goal towards the end of the season will not come as a surprise. And he 'proved something' as...",
          "image": "https://ichef.bbci.co.uk/ace/standard/240/cpsprodpb/5f75/live/9a10d780-1027-11f1-ab85-f7fb8d09b1b3.jpg"
        },
        {
          "title": "Eze torments Spurs again as leaders Arsenal win north London derby",
          "link": "https://www.bbc.com/sport/football/videos/cr73z495vyxo?at_medium=RSS&at_campaign=rss",
          "published": "2026-02-22",
          "summary": "Eberechi Eze torments Tottenham Hotspur again as Arsenal made a title statement of intent by restoring their lead at the top of the Premier League table to five points with victory in the north London...",
          "image": "https://ichef.bbci.co.uk/ace/standard/240/cpsprodpb/d67f/live/d6ef2ff0-1025-11f1-801d-ed3cff6bf876.jpg"
        },
        {
          "title": "Jimenez scores twice as Fulham leapfrog Sunderland into top half of table",
          "link": "https://www.bbc.com/sport/football/videos/c3wldnxdd5do?at_medium=RSS&at_campaign=rss",
          "published": "2026-02-22",
          "summary": "Raul Jimenez scores twice as Fulham end a run of three consecutive defeats, with a 3-1 win over Sunderland at the Stadium of Light in the Premier League.",
          "image": "https://ichef.bbci.co.uk/ace/standard/240/cpsprodpb/b018/live/3dc1fef0-1009-11f1-b048-c9424b2cf5fd.jpg"
        }
      ],
      "highlights": [
        {
          "title": "Premier League highlights this week - Week Highlights",
          "search_url": "https://www.youtube.com/results?search_query=Premier+League+highlights+this+week",
          "embed_id": null
        }
      ]
    },
    "championship": {
      "name": "Championship",
      "articles": [
        {
          "title": "Watch best of Scottish Championship & Leagues 1 & 2",
          "link": "https://www.bbc.com/sport/videos/cvg8ng9kn3yo?at_medium=RSS&at_campaign=rss",
          "published": "2026-02-23",
          "summary": "Watch the best of the action as Partick Thistle narrow the gap at the top of the Scottish Championship, honours are even between the top two in League 1, while East Kilbride extend their lead in Leagu...",
          "image": "https://ichef.bbci.co.uk/ace/standard/240/cpsprodpb/581f/live/07ad4210-1096-11f1-b048-c9424b2cf5fd.png"
        },
        {
          "title": "Shields dominates Crews-Dezurn again to remain undisputed",
          "link": "https://www.skysports.com/boxing/news/12040/13510972/claressa-shields-dominates-franchon-crews-dezurn-again-in-detroit-to-remain-undisputed-heavyweight-champion",
          "published": "2026-02-23",
          "summary": "Claressa Shields dominated Franchon Crews-Dezurn with a lopsided unanimous decision on Sunday night in Detroit, successfully defending her undisputed heavyweight championship.",
          "image": "https://e0.365dm.com/26/02/1920x1080/skysports-claressa-shields_7172476.jpg?20260223062343"
        },
        {
          "title": "Wrexham on march and West Brom's 'precarious position' - Sam Parkin's EFL takeaways",
          "link": "https://www.bbc.com/sport/football/articles/c93w9y00kp4o?at_medium=RSS&at_campaign=rss",
          "published": "2026-02-21",
          "summary": "BBC Final Score pundit Sam Parkin delivers his verdict on the big talking points across the Championship, League One and League Two.",
          "image": "https://ichef.bbci.co.uk/ace/standard/240/cpsprodpb/93db/live/2d4a1790-801e-11f0-ab3e-bd52082cd0ae.png"
        },
        {
          "title": "'Commitment, honesty & endeavour' fuelling Wrexham",
          "link": "https://www.bbc.com/sport/football/articles/cy03wngny40o?at_medium=RSS&at_campaign=rss",
          "published": "2026-02-21",
          "summary": "Phil Parkinson feels Wrexham's \"sheer commitment, honesty and endeavour\" was pivotal to their dramatic 5-3 win over Ipswich Town in the Championship.",
          "image": "https://ichef.bbci.co.uk/ace/standard/240/cpsprodpb/5052/live/786ff0a0-0f48-11f1-9a2a-8fa7cf422a25.jpg"
        }
      ],
      "highlights": [
        {
          "title": "Championship highlights this week - Week Highlights",
          "search_url": "https://www.youtube.com/results?search_query=Championship+highlights+this+week",
          "embed_id": null
        }
      ]
    },
    "league_one": {
      "name": "League One",
      "articles": [
        {
          "title": "Football Daily",
          "link": "https://www.bbc.co.uk/sounds/play/m002rvxp?at_medium=RSS&at_campaign=rss",
          "published": "2026-02-22",
          "summary": "It's ANOTHER Ebere Eze-inspired 4-1 North London derby victory but City are close behind!",
          "image": "https://ichef.bbci.co.uk/images/ic/240x135/p0n2n95j.jpg"
        }
      ],
      "highlights": [
        {
          "title": "League One highlights this week - Week Highlights",
          "search_url": "https://www.youtube.com/results?search_query=League+One+highlights+this+week",
          "embed_id": null
        }
      ]
    },
    "league_two": {
      "name": "League Two",
      "articles": [],
      "highlights": [
        {
          "title": "League Two highlights this week - Week Highlights",
          "search_url": "https://www.youtube.com/results?search_query=League+Two+highlights+this+week",
          "embed_id": null
        }
      ]
    },
    "world_cup": {
      "name": "World Cup",
      "articles": [],
      "highlights": [
        {
          "title": "World Cup highlights this week - Week Highlights",
          "search_url": "https://www.youtube.com/results?search_query=World+Cup+highlights+this+week",
          "embed_id": null
        }
      ]
    }
  },
  "standout_moments": [
    {
      "moment": "Arsenal pass derby test of nerve as title race looks set to go to wire",
      "link": "https://www.bbc.com/sport/football/articles/cx2g3gq37xvo?at_medium=RSS&at_campaign=rss"
    },
    {
      "moment": "Eze torments Spurs again as leaders Arsenal win north London derby",
      "link": "https://www.bbc.com/sport/football/videos/cr73z495vyxo?at_medium=RSS&at_campaign=rss"
    },
    {
      "moment": "Referee disallowed Spurs goal for 'soft' push - Given",
      "link": "https://www.bbc.com/sport/football/videos/c20zp25g85yo?at_medium=RSS&at_campaign=rss"
    },
    {
      "moment": "'Who's going to get this fine?' - Arteta on derby technology delays",
      "link": "https://www.bbc.com/sport/articles/c39wzwpdel0o?at_medium=RSS&at_campaign=rss"
    },
    {
      "moment": "Football Daily",
      "link": "https://www.bbc.co.uk/sounds/play/m002rvxp?at_medium=RSS&at_campaign=rss"
    },
    {
      "moment": "'Drive and hunger' take Milner to Premier League appearance record",
      "link": "https://www.bbc.com/sport/football/articles/cjrqdnj2199o?at_medium=RSS&at_campaign=rss"
    },
    {
      "moment": "'Commitment, honesty & endeavour' fuelling Wrexham",
      "link": "https://www.bbc.com/sport/football/articles/cy03wngny40o?at_medium=RSS&at_campaign=rss"
    },
    {
      "moment": "'I still feel I can contribute' - Milner on breaking Premier League record",
      "link": "https://www.bbc.com/sport/football/videos/czj1kyv4xvdo?at_medium=RSS&at_campaign=rss"
    },
    {
      "moment": "Farke 'proud' of his warriors despite disappointment with Villa draw",
      "link": "https://www.bbc.com/sport/football/videos/c3dz4p1308no?at_medium=RSS&at_campaign=rss"
    },
    {
      "moment": "Littler victory in Poland can fuel Premier League comeback in Belfast",
      "link": "https://www.skysports.com/darts/news/12040/13510833/luke-littler-believes-victory-in-poland-can-fuel-a-premier-league-darts-comeback-starting-in-belfast-on-thursday"
    }
  ]
}