{
  "generated_date": "2026-04-19",
  "week_ending": "April 19, 2026",
  "divisions": {
    "premier_league": {
      "name": "Premier League",
      "articles": [
        {
          "title": "Why Man City 'leg-beaters' can make difference against Arsenal - Pulis",
          "link": "https://www.bbc.com/sport/football/articles/cnv88q6l9q6o?at_medium=RSS&at_campaign=rss",
          "published": "2026-04-19",
          "summary": "Tony Pulis explains why Manchester City's attacking players could prove to be their match-winners in Sunday's Premier League title showdown with leaders Arsenal.",
          "image": "https://ichef.bbci.co.uk/ace/standard/240/cpsprodpb/598f/live/4d792f60-3bd0-11f1-96d4-558d846d3c9d.jpg"
        },
        {
          "title": "How will Arteta set Arsenal up for Man City showdown?",
          "link": "https://www.bbc.com/sport/football/articles/c1eq2xdyg3wo?at_medium=RSS&at_campaign=rss",
          "published": "2026-04-19",
          "summary": "Novel solutions, no matter how small, might decide the Premier League title. We take a closer look at how Arsenal have played recently and what this means for the run-in.",
          "image": "https://ichef.bbci.co.uk/ace/standard/240/cpsprodpb/0b4c/live/9f5e36d0-3b45-11f1-9e4f-cdab8de3fb0a.jpg"
        },
        {
          "title": "First 'daylight' offside goal scored in Canada",
          "link": "https://www.bbc.com/sport/football/articles/c04xk952zd4o?at_medium=RSS&at_campaign=rss",
          "published": "2026-04-19",
          "summary": "The first goal allowed under the experimental \"daylight\" \u200boffside rule is scored in Canada",
          "image": "https://ichef.bbci.co.uk/ace/standard/240/cpsprodpb/d5ce/live/e725b870-3bbe-11f1-8a14-19337d79de52.jpg"
        },
        {
          "title": "Wild celebrations to verge of tears -  time running out for Spurs",
          "link": "https://www.bbc.com/sport/football/articles/c1l9yyp28peo?at_medium=RSS&at_campaign=rss",
          "published": "2026-04-18",
          "summary": "Scenes of celebration turned to bitter disappointment as Tottenham's hopes of avoiding relegation from the Premier League were dealt a devastating blow against Brighton.",
          "image": "https://ichef.bbci.co.uk/ace/standard/240/cpsprodpb/ccc3/live/f9c657f0-3bb9-11f1-b909-5fca5a802d88.jpg"
        },
        {
          "title": "Carrick silences doubters as Man Utd close on Champions League",
          "link": "https://www.bbc.com/sport/football/articles/cly67vpyx1jo?at_medium=RSS&at_campaign=rss",
          "published": "2026-04-18",
          "summary": "Manchester United beat Chelsea to move closer to a Champions League return and silence the growing Michael Carrick doubters.",
          "image": "https://ichef.bbci.co.uk/ace/standard/240/cpsprodpb/e277/live/f5865860-3b79-11f1-8a63-e3fa357a6747.jpg"
        },
        {
          "title": "How Hampton's heroics bailed out Lionesses in win against Iceland",
          "link": "https://www.bbc.com/sport/football/articles/clyx9zgvr4po?at_medium=RSS&at_campaign=rss",
          "published": "2026-04-18",
          "summary": "Goalkeeper Hannah Hampton says she just \"did my job\" in pulling off three crucial late saves as England held on to beat Iceland 1-0.",
          "image": "https://ichef.bbci.co.uk/ace/standard/240/cpsprodpb/72f5/live/69fcdc20-3b69-11f1-82d7-e5c9d3ef5ba2.jpg"
        },
        {
          "title": "Howe's biggest Newcastle challenge yet as questions grow on his future",
          "link": "https://www.bbc.com/sport/football/articles/c203y3ykv6no?at_medium=RSS&at_campaign=rss",
          "published": "2026-04-18",
          "summary": "Newcastle are languishing in 14th place in the Premier League following defeat by Bournemouth. Will manager Eddie Howe turn it around?",
          "image": "https://ichef.bbci.co.uk/ace/standard/240/cpsprodpb/d5a8/live/c333ea00-3b5e-11f1-879d-1b2f5c3919b8.jpg"
        },
        {
          "title": "Can Leeds feel safe from relegation after back-to-back wins?",
          "link": "https://www.bbc.com/sport/football/articles/cr4171dw46go?at_medium=RSS&at_campaign=rss",
          "published": "2026-04-18",
          "summary": "Leeds United are eight points above the Premier League drop zone after back-to-back wins - so can they feel safe from relegation?",
          "image": "https://ichef.bbci.co.uk/ace/standard/240/cpsprodpb/a075/live/9cae19e0-3b64-11f1-9d5c-8ba507d7dbde.jpg"
        },
        {
          "title": "Rutter scores late equaliser to deny Spurs crucial win",
          "link": "https://www.bbc.com/sport/football/videos/cr41772xd92o?at_medium=RSS&at_campaign=rss",
          "published": "2026-04-18",
          "summary": "Tottenham remain in the bottom three and are denied their first Premier League victory since December as Georginio Rutter scores a late equaliser for Brighton as the two sides draw 2-2 at the Tottenha...",
          "image": "https://ichef.bbci.co.uk/ace/standard/240/cpsprodpb/1dae/live/e5febbb0-3b5d-11f1-9d5c-8ba507d7dbde.jpg"
        },
        {
          "title": "Man Utd boost Champions League hopes with victory at Chelsea",
          "link": "https://www.bbc.com/sport/football/videos/ceqwde99q49o?at_medium=RSS&at_campaign=rss",
          "published": "2026-04-18",
          "summary": "Manchester United move closer to booking a place in next seasons Champions League after Matheus Cunha scores the only goal of the game in their 1-0 win over Chelsea at Stamford Bridge.",
          "image": "https://ichef.bbci.co.uk/ace/standard/240/cpsprodpb/ad96/live/f3423d20-3b6b-11f1-8606-05fe34b06e1b.jpg"
        },
        {
          "title": "Leeds hit three past Wolves to move closer to survival",
          "link": "https://www.bbc.com/sport/football/videos/cy81w215ze9o?at_medium=RSS&at_campaign=rss",
          "published": "2026-04-18",
          "summary": "Leeds moved a step closer to securing their Premier League survival as they beat Wolves 3-0 at Elland Road.",
          "image": "https://ichef.bbci.co.uk/ace/standard/240/cpsprodpb/fd31/live/71608420-3b4c-11f1-8606-05fe34b06e1b.jpg"
        },
        {
          "title": "Bournemouth extend unbeaten run with victory at Newcastle",
          "link": "https://www.bbc.com/sport/football/videos/c6251dnn9j7o?at_medium=RSS&at_campaign=rss",
          "published": "2026-04-18",
          "summary": "Bournemouth extend their unbeaten run in the Premier League to 13 games after beating Newcastle 2-1 at St. James' Park.",
          "image": "https://ichef.bbci.co.uk/ace/standard/240/cpsprodpb/3a86/live/890d0080-3b4c-11f1-879d-1b2f5c3919b8.jpg"
        },
        {
          "title": "Brentford and Fulham share the points after goalless draw",
          "link": "https://www.bbc.com/sport/football/videos/c705y5893pyo?at_medium=RSS&at_campaign=rss",
          "published": "2026-04-18",
          "summary": "Brentford draw their fifth-consecutive Premier League game as they draw 0-0 with Fulham at the Gtech Community Stadium.",
          "image": "https://ichef.bbci.co.uk/ace/standard/240/cpsprodpb/1943/live/b864d3b0-3b3f-11f1-8606-05fe34b06e1b.jpg"
        },
        {
          "title": "How Porro let Tottenham down in defensive areas against Brighton",
          "link": "https://www.bbc.com/sport/football/videos/cm2k0gjnx0eo?at_medium=RSS&at_campaign=rss",
          "published": "2026-04-18",
          "summary": "Match of the Day pundit Ashley Williams praises Pedro Porro's attacking play but thinks he needs to do more defensively with his team in a relegation battle.",
          "image": "https://ichef.bbci.co.uk/ace/standard/240/cpsprodpb/2886/live/bd6b6a80-3b72-11f1-8606-05fe34b06e1b.jpg"
        },
        {
          "title": "We need to find a solution to win games - De Zerbi",
          "link": "https://www.bbc.com/sport/football/videos/c2d8yyl002yo?at_medium=RSS&at_campaign=rss",
          "published": "2026-04-18",
          "summary": "Tottenham manager Roberto De Zerbi believes his side deserved to win, as Spurs were denied their first win in the league since December after conceding a late equaliser to draw 2-2 with Brighton at th...",
          "image": "https://ichef.bbci.co.uk/ace/standard/240/cpsprodpb/9617/live/a0cdfc00-3b5c-11f1-8606-05fe34b06e1b.jpg"
        }
      ],
      "highlights": [
        {
          "title": "Premier League highlights this week - Week Highlights",
          "search_url": "https://www.youtube.com/results?search_query=Premier+League+highlights+this+week",
          "embed_id": null
        }
      ]
    },
    "championship": {
      "name": "Championship",
      "articles": [
        {
          "title": "Toure hat-trick steers Norwich past Bristol City",
          "link": "https://www.skysports.com/football/bristol-city-vs-norwich-city/report/534824",
          "published": "2026-04-18",
          "summary": "Mohamed Toure netted a second-half hat-trick as&#160;Norwich&#160;came from behind to beat Roy Hodgson's Bristol City 4-2 in a mid-table Championship battle at Ashton Gate.",
          "image": "https://e1.365dm.com/26/04/1920x1080/skysports-efl-championship_7223681.jpg?20260418170458"
        },
        {
          "title": "Charlton held by Sheff Wed but edge closer to safety",
          "link": "https://www.skysports.com/football/sheffield-wednesday-vs-charlton-athletic/report/534831",
          "published": "2026-04-18",
          "summary": "Charlton&#160;edged nearer to securing Championship safety as they drew 1-1 with Sheffield Wednesday.",
          "image": "https://e2.365dm.com/26/04/1920x1080/skysports-sheffield-wednesday_7223701.jpg?20260418170937"
        }
      ],
      "highlights": [
        {
          "title": "Championship highlights this week - Week Highlights",
          "search_url": "https://www.youtube.com/results?search_query=Championship+highlights+this+week",
          "embed_id": null
        }
      ]
    },
    "league_one": {
      "name": "League One",
      "articles": [
        {
          "title": "Bromley promoted to League One for first time",
          "link": "https://www.bbc.com/sport/football/articles/cy713v8ln2ro?at_medium=RSS&at_campaign=rss",
          "published": "2026-04-18",
          "summary": "Bromley are promoted to League One for the first time in the club's history after Notts County's defeat by Barnet.",
          "image": "https://ichef.bbci.co.uk/ace/standard/240/cpsprodpb/5212/live/9a0f6e20-3a3b-11f1-826b-272fcb9e69bd.jpg"
        },
        {
          "title": "Bromley promoted to League One for first time in their history",
          "link": "https://www.skysports.com/football/news/12040/13530042/bromley-promoted-to-league-one-for-the-first-time-in-their-history",
          "published": "2026-04-18",
          "summary": "Bromley have been promoted to League One for the first time in their history with two games of the season to spare.",
          "image": "https://e0.365dm.com/26/04/1920x1080/skysports-bromley-fc_7216830.jpg?20260411111207"
        }
      ],
      "highlights": [
        {
          "title": "League One highlights this week - Week Highlights",
          "search_url": "https://www.youtube.com/results?search_query=League+One+highlights+this+week",
          "embed_id": null
        }
      ]
    },
    "league_two": {
      "name": "League Two",
      "articles": [],
      "highlights": [
        {
          "title": "League Two highlights this week - Week Highlights",
          "search_url": "https://www.youtube.com/results?search_query=League+Two+highlights+this+week",
          "embed_id": null
        }
      ]
    },
    "world_cup": {
      "name": "World Cup",
      "articles": [],
      "highlights": [
        {
          "title": "World Cup highlights this week - Week Highlights",
          "search_url": "https://www.youtube.com/results?search_query=World+Cup+highlights+this+week",
          "embed_id": null
        }
      ]
    }
  },
  "standout_moments": [
    {
      "moment": "'What a goal!' - Mitoma's STUNNING volley brings Brighton level before the break!",
      "link": "https://www.skysports.com/watch/video/13533536/goal-k-mitoma-453-tottenham-hotspur-1-1-brighton"
    },
    {
      "moment": "Toure hat-trick steers Norwich past Bristol City",
      "link": "https://www.skysports.com/football/bristol-city-vs-norwich-city/report/534824"
    }
  ]
}