{
  "generated_date": "2026-03-19",
  "week_ending": "March 19, 2026",
  "divisions": {
    "premier_league": {
      "name": "Premier League",
      "articles": [
        {
          "title": "Slot needed a performance - and Liverpool delivered one",
          "link": "https://www.bbc.com/sport/football/articles/c99j92p8n5ro?at_medium=RSS&at_campaign=rss",
          "published": "2026-03-19",
          "summary": "Despite a difficult domestic campaign, Liverpool produce one of their best displays of the season against Galatasaray in the Champions League.",
          "image": "https://ichef.bbci.co.uk/ace/standard/240/cpsprodpb/04f3/live/2890d050-2324-11f1-934f-036468834728.jpg"
        },
        {
          "title": "The 15-year-old Man Utd prodigy still too young to play senior football",
          "link": "https://www.bbc.com/sport/football/articles/ckg8gp88m8xo?at_medium=RSS&at_campaign=rss",
          "published": "2026-03-19",
          "summary": "At 15, Manchester United's JJ Gabriel is too young to play in the Premier League but he is already showing clear signs he is a huge talent.",
          "image": "https://ichef.bbci.co.uk/ace/standard/240/cpsprodpb/4bf3/live/2c6706a0-2319-11f1-934f-036468834728.jpg"
        },
        {
          "title": "Why Real Madrid have 'complete confidence' in teenager Pitarch",
          "link": "https://www.bbc.com/sport/football/articles/cm21274xn43o?at_medium=RSS&at_campaign=rss",
          "published": "2026-03-19",
          "summary": "When an 18-year-old makes Real Madrid history in a crucial Champions League tie against Manchester City, it inevitably draws acclaim and attention. BBC Sport takes a look at rising star Thiago Pitarch...",
          "image": "https://ichef.bbci.co.uk/ace/standard/240/cpsprodpb/87c0/live/976545c0-22ce-11f1-b72c-95dabe3e6755.jpg"
        },
        {
          "title": "England still in good position for fifth Champions League spot despite exits",
          "link": "https://www.skysports.com/football/news/12040/13521648/fifth-champions-league-place-england-still-in-good-position-in-co-efficient-table-for-extra-spot-despite-last-16-eliminations",
          "published": "2026-03-19",
          "summary": "England are still in a commanding position to secure a fifth Champions League place for the 2026/27 campaign - despite a disappointing set of results in the last-16 stage.",
          "image": "https://e2.365dm.com/26/01/1920x1080/skysports-champions-league_7141841.jpg?20260121181900"
        },
        {
          "title": "Slot defies doubters as Liverpool & Salah deliver season's 'best performance'",
          "link": "https://www.skysports.com/football/news/12040/13521642/liverpool-boss-arne-slot-defies-doubters-as-mo-salah-inspires-best-performance-of-the-season-in-champions-league-win",
          "published": "2026-03-19",
          "summary": "Liverpool delivered their &#8220;best performance of the season&#8221; at the crucial time for Arne Slot. Finally, we saw why they are Premier League champions and Anfield got its team back.",
          "image": "https://e0.365dm.com/26/03/1920x1080/skysports-salah-mohamed-ekitike_7197098.jpg?20260319084413"
        },
        {
          "title": "'Archie Gray, WOW!' | Hope for Spurs and Tudor after positive Atletico display",
          "link": "https://www.skysports.com/watch/video/13521640/positives-for-igor-tudor-and-spurs-after-cl-win-the-verdict",
          "published": "2026-03-19",
          "summary": "Sky Sports reporter Michael Bridge explains why Igor Tudor can take plenty of positives from Wednesday's Champions League exit into their crucial clash with Nottingham Forest this weekend.",
          "image": "https://e0.365dm.com/26/03/1920x1080/skysports-spurs-michael-bridge_7197067.jpg?20260319073753"
        },
        {
          "title": "Van Veen pulls out of Premier League Darts in Dublin",
          "link": "https://www.skysports.com/darts/news/12040/13521651/premier-league-darts-gian-van-veen-withdraws-from-night-seven-in-dublin-due-to-kidney-stones",
          "published": "2026-03-19",
          "summary": "Gian van Veen has withdrawn from Night Seven in the Premier League in Dublin after being diagnosed with kidney stones.&#160;",
          "image": "https://e1.365dm.com/26/02/1920x1080/skysports-gian-van-veen-darts_7162472.jpg?20260211190103"
        },
        {
          "title": "Four English teams out in 24 hours - what happened and why?",
          "link": "https://www.bbc.com/sport/football/articles/cqxd55dxrejo?at_medium=RSS&at_campaign=rss",
          "published": "2026-03-18",
          "summary": "With just two out of six Premier League teams progressing to the Champions League quarter-finals, what went wrong for the English sides?",
          "image": "https://ichef.bbci.co.uk/ace/standard/240/cpsprodpb/4502/live/47edd8d0-22de-11f1-a79a-77e93010d956.jpg"
        },
        {
          "title": "Credit to Tudor - is he turning around Spurs side who looked lost?",
          "link": "https://www.bbc.com/sport/football/articles/c5y5y8nxl7xo?at_medium=RSS&at_campaign=rss",
          "published": "2026-03-18",
          "summary": "Tottenham can take encouragement in their battle for Premier League survival despite a Champions League exit, writes Phil McNulty.",
          "image": "https://ichef.bbci.co.uk/ace/standard/240/cpsprodpb/0578/live/99c66370-231f-11f1-b297-95b0a0a8331e.jpg"
        },
        {
          "title": "Liverpool ease past Galatasaray to reach quarter-finals",
          "link": "https://www.bbc.com/sport/football/videos/c1mjy4z8v9ro?at_medium=RSS&at_campaign=rss",
          "published": "2026-03-18",
          "summary": "Liverpool beat Galatasaray 4-0 at Anfield to advance 4-1 on aggregate in the last 16 of the Champions League to set up a quarter-final tie against Paris Saint-Germain.",
          "image": "https://ichef.bbci.co.uk/ace/standard/240/cpsprodpb/17e3/live/87402030-2318-11f1-a79a-77e93010d956.jpg"
        },
        {
          "title": "'One of a kind' Messi hits 900 career goals - numbers behind milestone",
          "link": "https://www.bbc.com/sport/football/articles/c0rj25g225ro?at_medium=RSS&at_campaign=rss",
          "published": "2026-03-18",
          "summary": "After Lionel Messi scored his 900th career goal on Wednesday, BBC Sport looks at the numbers behind the \"insane\" achievement.",
          "image": "https://ichef.bbci.co.uk/ace/standard/240/cpsprodpb/13e7/live/ad3814f0-2322-11f1-90eb-61042da00424.jpg"
        },
        {
          "title": "From hope to humiliation, so what now for Newcastle?",
          "link": "https://www.bbc.com/sport/football/articles/cjene4jj8xwo?at_medium=RSS&at_campaign=rss",
          "published": "2026-03-18",
          "summary": "After a humbling Champions League last-16 defeat by Barcelona, what next for Eddie Howe's Newcastle?",
          "image": "https://ichef.bbci.co.uk/ace/standard/240/cpsprodpb/e7f6/live/2f22d900-231e-11f1-934f-036468834728.jpg"
        },
        {
          "title": "Is Premier League still on for fifth Champions League spot?",
          "link": "https://www.bbc.com/sport/football/articles/cwy9yxw8dy9o?at_medium=RSS&at_campaign=rss",
          "published": "2026-03-18",
          "summary": "Could the Premier League get an extra place in the Champions League again? This is how it looks after the last 16.",
          "image": "https://ichef.bbci.co.uk/ace/standard/240/cpsprodpb/eb03/live/b14e5090-230e-11f1-adfb-71e745538879.jpg"
        },
        {
          "title": "Tudor gets first Tottenham win but Spurs lose tie against Atletico Madrid",
          "link": "https://www.bbc.com/sport/football/videos/cx2g49094m7o?at_medium=RSS&at_campaign=rss",
          "published": "2026-03-18",
          "summary": "Tottenham beat Atletico Madrid 3-2 in the second leg of their last 16 tie in the Champions League, securing a first win for manager Igor Tudor but it's not enough to win the tie, as Atletico win 7-5 o...",
          "image": "https://ichef.bbci.co.uk/ace/standard/240/cpsprodpb/722a/live/5b7eb0a0-2319-11f1-b297-95b0a0a8331e.jpg"
        },
        {
          "title": "Newcastle collapse at Nou Camp as Barcelona score seven",
          "link": "https://www.bbc.com/sport/football/videos/c0q3ykgy9wwo?at_medium=RSS&at_campaign=rss",
          "published": "2026-03-18",
          "summary": "Newcastle undergo a second-half collapse at the Nou Camp as they lose 7-2 on the night and 8-3 on aggregate to Barcelona in the last 16 of the Champions League.",
          "image": "https://ichef.bbci.co.uk/ace/standard/240/cpsprodpb/66bd/live/b77c6420-2304-11f1-934f-036468834728.jpg"
        }
      ],
      "highlights": [
        {
          "title": "Premier League highlights this week - Week Highlights",
          "search_url": "https://www.youtube.com/results?search_query=Premier+League+highlights+this+week",
          "embed_id": null
        }
      ]
    },
    "championship": {
      "name": "Championship",
      "articles": [
        {
          "title": "Championship faces financial 'catastrophe' warns Portsmouth owner Eisner",
          "link": "https://www.bbc.com/sport/football/articles/ce3g3ygjkjvo?at_medium=RSS&at_campaign=rss",
          "published": "2026-03-18",
          "summary": "Portsmouth chairman Michael Eisner warns of looming financial catastrophe in the Championship after Pompey became the latest club to post a loss.",
          "image": "https://ichef.bbci.co.uk/ace/standard/240/cpsprodpb/ca75/live/266e63f0-22c0-11f1-9a45-07ac962dc928.jpg"
        },
        {
          "title": "Do you want VAR in the Championship?",
          "link": "https://www.bbc.com/sport/football/articles/cwy6zl35z0ro?at_medium=RSS&at_campaign=rss",
          "published": "2026-03-18",
          "summary": "BBC Sport asks fans whether they want VAR to be introduced in the Championship.",
          "image": "https://ichef.bbci.co.uk/ace/standard/240/cpsprodpb/483b/live/a12cbf00-1e2a-11f1-801d-ed3cff6bf876.jpg"
        },
        {
          "title": "Southampton beat Norwich to leapfrog Wrexham into play-off places",
          "link": "https://www.skysports.com/football/southampton-vs-norwich-city/report/534748",
          "published": "2026-03-18",
          "summary": "Finn Azaz's first-half strike was enough to secure a 1-0 victory over Norwich and send Southampton into the Championship play-off places for the first time since the opening weekend.",
          "image": "https://e2.365dm.com/26/03/1920x1080/skysports-efl-championship_7196849.jpg?20260318204516"
        }
      ],
      "highlights": [
        {
          "title": "Championship highlights this week - Week Highlights",
          "search_url": "https://www.youtube.com/results?search_query=Championship+highlights+this+week",
          "embed_id": null
        }
      ]
    },
    "league_one": {
      "name": "League One",
      "articles": [],
      "highlights": [
        {
          "title": "League One highlights this week - Week Highlights",
          "search_url": "https://www.youtube.com/results?search_query=League+One+highlights+this+week",
          "embed_id": null
        }
      ]
    },
    "league_two": {
      "name": "League Two",
      "articles": [],
      "highlights": [
        {
          "title": "League Two highlights this week - Week Highlights",
          "search_url": "https://www.youtube.com/results?search_query=League+Two+highlights+this+week",
          "embed_id": null
        }
      ]
    },
    "world_cup": {
      "name": "World Cup",
      "articles": [
        {
          "title": "History made as Messi hits 900 goals",
          "link": "https://www.bbc.com/sport/football/videos/cn0z00ved8jo?at_medium=RSS&at_campaign=rss",
          "published": "2026-03-19",
          "summary": "Lionel Messi's scores his 900th career goal in Inter Miami's match against Nashville SC in the Concacaf Champions Cup. The 38-year-old joins an elite club alongside Cristiano Ronaldo and Brazilian leg...",
          "image": "https://ichef.bbci.co.uk/ace/standard/240/cpsprodpb/a5a1/live/4e037030-2375-11f1-a79a-77e93010d956.jpg"
        },
        {
          "title": "Senegal government alleges corruption after Morocco awarded Afcon title",
          "link": "https://www.bbc.com/sport/football/articles/cwygyq495j8o?at_medium=RSS&at_campaign=rss",
          "published": "2026-03-18",
          "summary": "The Senegalese government calls for an \"independent international investigation\" at the Confederation of African Football after it stripped Senegal of the Africa Cup of Nations title.",
          "image": "https://ichef.bbci.co.uk/ace/standard/240/cpsprodpb/7ad3/live/fdca7a50-22bb-11f1-9a45-07ac962dc928.jpg"
        }
      ],
      "highlights": [
        {
          "title": "World Cup highlights this week - Week Highlights",
          "search_url": "https://www.youtube.com/results?search_query=World+Cup+highlights+this+week",
          "embed_id": null
        }
      ]
    }
  },
  "standout_moments": [
    {
      "moment": "'The longest VAR check in history' - the fallout from shock Afcon decision",
      "link": "https://www.bbc.com/sport/football/articles/c89k911qkp5o?at_medium=RSS&at_campaign=rss"
    },
    {
      "moment": "Five-star Sporting produce brilliant comeback to shock Bodo/Glimt",
      "link": "https://www.bbc.com/sport/football/videos/c70kypwpdkgo?at_medium=RSS&at_campaign=rss"
    }
  ]
}